thing3/__init__.py
thing3/rat.gif
thing3/win.png
thingthingthingj-0.69.dist-info/LICENSE
thingthingthingj-0.69.dist-info/METADATA
thingthingthingj-0.69.dist-info/WHEEL
thingthingthingj-0.69.dist-info/top_level.txt
thingthingthingj-0.69.dist-info/RECORD
